python_cloud_utils_289772/__init__.py
python_cloud_utils_289772-0.1.0.dist-info/METADATA
python_cloud_utils_289772-0.1.0.dist-info/WHEEL
python_cloud_utils_289772-0.1.0.dist-info/top_level.txt
python_cloud_utils_289772-0.1.0.dist-info/RECORD
