Metadata-Version: 2.4
Name: python-cloud-utils-289772
Version: 0.1.0
Summary: AWS configuration utilities for Python applications
License: MIT
Project-URL: Homepage, https://github.com/example/python-cloud-utils-289772
Project-URL: Bug Tracker, https://github.com/example/python-cloud-utils-289772/issues
Classifier: Development Status :: 3 - Alpha
Classifier: Intended Audience :: Developers
Classifier: License :: OSI Approved :: MIT License
Classifier: Programming Language :: Python :: 3
Classifier: Programming Language :: Python :: 3.8
Classifier: Programming Language :: Python :: 3.9
Classifier: Programming Language :: Python :: 3.10
Classifier: Programming Language :: Python :: 3.11
Requires-Python: >=3.8
Requires-Dist: boto3>=1.26.0
